arcturus/__init__.py
arcturus/arcturus_buildkit.py
arcturus/data_arcturus.py
arcturus_buildkit-0.2.1.dist-info/METADATA
arcturus_buildkit-0.2.1.dist-info/WHEEL
arcturus_buildkit-0.2.1.dist-info/top_level.txt
arcturus_buildkit-0.2.1.dist-info/RECORD
