Metadata-Version: 2.4
Name: arcturus-buildkit
Version: 0.2.1
Summary: Lightweight NLP and supervised ML chatbot framework in pure Python
Home-page: 
Author: FlameZI0
Author-email: abdulrehmanshoaib136@gmail.com
Classifier: Programming Language :: Python :: 3
Classifier: License :: OSI Approved :: MIT License
Classifier: Operating System :: OS Independent
Requires-Python: >=3.9
Dynamic: author
Dynamic: author-email
Dynamic: classifier
Dynamic: description
Dynamic: description-content-type
Dynamic: requires-python
Dynamic: summary
